{
  "annotations": {
    "changeLogDate": 20250110000000,
    "changelogDate": "20250111030648",
    "entityPackage": "article",
    "skipFakeData": true
  },
  "applications": ["appCoffeeHubApi"],
  "dto": "mapstruct",
  "fields": [
    {
      "fieldName": "categoryID",
      "fieldType": "Long",
      "fieldValidateRules": ["required"]
    },
    {
      "fieldName": "bodyId",
      "fieldType": "Long",
      "fieldValidateRules": ["required"]
    },
    {
      "fieldName": "authorId",
      "fieldType": "Long",
      "fieldValidateRules": ["required"]
    },
    {
      "fieldName": "title",
      "fieldType": "String",
      "fieldValidateRules": ["required"]
    },
    {
      "fieldName": "slug",
      "fieldType": "String"
    },
    {
      "fieldName": "subTitle",
      "fieldType": "String"
    },
    {
      "fieldName": "thumbnailUrl",
      "fieldType": "String"
    },
    {
      "fieldName": "readingTime",
      "fieldType": "Integer"
    },
    {
      "fieldName": "isPinned",
      "fieldType": "Boolean"
    },
    {
      "fieldName": "deleted",
      "fieldType": "Boolean"
    },
    {
      "fieldName": "createdAt",
      "fieldType": "Instant",
      "fieldValidateRules": ["required"]
    },
    {
      "fieldName": "createdBy",
      "fieldType": "String"
    },
    {
      "fieldName": "updatedAt",
      "fieldType": "Instant"
    },
    {
      "fieldName": "updatedBy",
      "fieldType": "String"
    }
  ],
  "name": "Articles",
  "pagination": "pagination",
  "relationships": [],
  "searchEngine": "no",
  "service": "serviceClass"
}
